simwrapper/FlaskApp.py
simwrapper/GunicornServer.py
simwrapper/MiniFileServer.py
simwrapper/SimpleH5File.py
simwrapper/__init__.py
simwrapper/cli.py
simwrapper/sites.py
simwrapper/config/gunicorn_config.py
simwrapper/config/nginx.conf
simwrapper/config/simwrapper-flask-app.service
simwrapper/config/simwrapper-rclone.service
simwrapper/config/supervisord.conf
simwrapper/static/404.html
simwrapper/static/404.html.bak
simwrapper/static/CNAME
simwrapper/static/README.md
simwrapper/static/icon-atlas.png
simwrapper/static/index.html
simwrapper/static/sax-wasm.wasm
simwrapper/static/sql-wasm.wasm
simwrapper/static/tu-logo-circle.jpg
simwrapper/static/tu-logo-circle.png
simwrapper/static/tu-logo.png
simwrapper/static/assets/AggregateDatasetStreamer.worker-BAkFzLI9.js
simwrapper/static/assets/AggregateOd-BWyxbgD3.css
simwrapper/static/assets/AggregateOd-BsBO-8aU.js
simwrapper/static/assets/BackgroundLayers-CUd5LA7y.js
simwrapper/static/assets/BackgroundMapOnTop-DQly83Xo.js
simwrapper/static/assets/BackgroundMapOnTop-DptOe2tm.css
simwrapper/static/assets/CalculationTable-D3eIayK6.js
simwrapper/static/assets/CalculationTable-ie-f6C8y.css
simwrapper/static/assets/CarrierViewer-BgfQYLk7.css
simwrapper/static/assets/CarrierViewer-WQZBHXFs.js
simwrapper/static/assets/CollapsiblePanel-D7Qg4ara.js
simwrapper/static/assets/CollapsiblePanel-zCvUtCGk.css
simwrapper/static/assets/ColorsAndWidths-CaSMrknU.js
simwrapper/static/assets/CoordinateConverter.worker-BUgBAv_F.js
simwrapper/static/assets/Coords-C-Mhj230.js
simwrapper/static/assets/CsvGzipParser.worker-CmRyigJZ.js
simwrapper/static/assets/DashboardDataManager-DOwC_6nC.js
simwrapper/static/assets/DataFetcher.worker-BxRJWgFP.js
simwrapper/static/assets/DrawingTool-Cxz0mWSd.css
simwrapper/static/assets/DrawingTool-DQR36Aq1.js
simwrapper/static/assets/EmbedView-Bf-3554F.js
simwrapper/static/assets/EmbedView-DpHMbeVt.css
simwrapper/static/assets/ErrorPanel-BC8GbRnV.css
simwrapper/static/assets/ErrorPanel-Bv11F2tj.js
simwrapper-4.3.4.dist-info/METADATA
simwrapper-4.3.4.dist-info/WHEEL
simwrapper-4.3.4.dist-info/entry_points.txt
simwrapper-4.3.4.dist-info/licenses/LICENSE.txt
simwrapper-4.3.4.dist-info/RECORD
