Metadata-Version: 2.4
Name: simwrapper
Version: 4.3.4
Summary: SimWrapper command line tools
Project-URL: Homepage, https://docs.simwrapper.app
Project-URL: Repository, https://github.com/simwrapper/simwrapper-python-tools
License-Expression: GPL-3.0-or-later
License-File: LICENSE.txt
Requires-Python: >=3.9
Requires-Dist: blosc>=1.11.3
Requires-Dist: build>=1.2.2.post1
Requires-Dist: click>=8.0
Requires-Dist: flask-compress>=1.18
Requires-Dist: flask-cors>=5.0.1
Requires-Dist: flask-restful>=0.3.10
Requires-Dist: flask>=3.1.0
Requires-Dist: gunicorn>=23.0.0
Requires-Dist: openmatrix>=0.3.5.0
Requires-Dist: pypatch>=1.0.2
Requires-Dist: pyyaml>=6.0.2
Requires-Dist: tables>=3.9.2
Requires-Dist: waitress>=3.0.2
